jinja2_minify.py
setup.py
Jinja2_Minify.egg-info/PKG-INFO
Jinja2_Minify.egg-info/SOURCES.txt
Jinja2_Minify.egg-info/dependency_links.txt
Jinja2_Minify.egg-info/requires.txt
Jinja2_Minify.egg-info/top_level.txt