Metadata-Version: 1.0
Name: Jinja2-Minify
Version: 0.1.1
Summary: Jinja2-Minify
Home-page: https://github.com/raicheff/jinja2-minify
Author: Boris Raicheff
Author-email: b@raicheff.com
License: UNKNOWN
Platform: UNKNOWN
